README.txt
setup.cfg
setup.py
gadgets/__init__.py
gadgets/coordinator.py
gadgets/errors.py
gadgets/gadget.py
gadgets/sockets.py
gadgets.egg-info/PKG-INFO
gadgets.egg-info/SOURCES.txt
gadgets.egg-info/dependency_links.txt
gadgets.egg-info/entry_points.txt
gadgets.egg-info/not-zip-safe
gadgets.egg-info/requires.txt
gadgets.egg-info/top_level.txt
gadgets/devices/__init__.py
gadgets/devices/device.py
gadgets/devices/trigger.py
gadgets/devices/cooler/__init__.py
gadgets/devices/cooler/cooler.py
gadgets/devices/cooler/cooler_factory.py
gadgets/devices/heater/__init__.py
gadgets/devices/heater/electric_heater.py
gadgets/devices/heater/electric_heater_factory.py
gadgets/devices/heater/pwm.py
gadgets/devices/heater/triggers/__init__.py
gadgets/devices/heater/triggers/temperature.py
gadgets/devices/input/__init__.py
gadgets/devices/input/adc.py
gadgets/devices/input/factory.py
gadgets/devices/input/input.py
gadgets/devices/input/io.py
gadgets/devices/motor/__init__.py
gadgets/devices/motor/motor.py
gadgets/devices/motor/motor_factory.py
gadgets/devices/motor/motor_io.py
gadgets/devices/motor/triggers/__init__.py
gadgets/devices/motor/triggers/counter.py
gadgets/devices/switch/__init__.py
gadgets/devices/switch/switch.py
gadgets/devices/switch/gpio/__init__.py
gadgets/devices/switch/gpio/factory.py
gadgets/devices/switch/shift_register/__init__.py
gadgets/devices/switch/shift_register/factory.py
gadgets/devices/switch/shift_register/io.py
gadgets/devices/switch/shift_register/server.py
gadgets/devices/switch/triggers/__init__.py
gadgets/devices/switch/triggers/switch_timer.py
gadgets/devices/switch/xbee/__init__.py
gadgets/devices/switch/xbee/factory.py
gadgets/devices/switch/xbee/io.py
gadgets/devices/switch/xbee/server.py
gadgets/devices/valve/__init__.py
gadgets/devices/valve/valve.py
gadgets/devices/valve/valve_factory.py
gadgets/devices/valve/triggers/__init__.py
gadgets/devices/valve/triggers/float.py
gadgets/devices/valve/triggers/gravity.py
gadgets/devices/valve/triggers/timer.py
gadgets/devices/valve/triggers/user.py
gadgets/devices/valve/triggers/volume_converter.py
gadgets/io/__init__.py
gadgets/io/adc.py
gadgets/io/counter.py
gadgets/io/gpio.py
gadgets/io/io.py
