Metadata-Version: 1.0
Name: gadgets
Version: 0.3.1
Summary: A physical computing framework
Home-page: https://bitbucket.org/cswank/gadgets
Author: Craig Swank
Author-email: craigswank@gmail.com
License: MIT
Keywords: beaglebone raspberry pi physical computing
Platform: UNKNOWN
